aioauth_fastapi/__init__.py
aioauth_fastapi/__version__.py
aioauth_fastapi/forms.py
aioauth_fastapi/router.py
aioauth_fastapi/utils.py
aioauth_fastapi-0.1.2.dist-info/LICENSE
aioauth_fastapi-0.1.2.dist-info/METADATA
aioauth_fastapi-0.1.2.dist-info/WHEEL
aioauth_fastapi-0.1.2.dist-info/top_level.txt
aioauth_fastapi-0.1.2.dist-info/RECORD
