Metadata-Version: 2.1
Name: aioauth-fastapi
Version: 0.1.2
Summary: aioauth integration for FastAPI.
Home-page: https://github.com/aliev/aioauth-fastapi
Author: Ali Aliyev
Author-email: ali@aliev.me
License: The MIT License (MIT)
Project-URL: Source, https://github.com/aliev/aioauth-fastapi
Keywords: asyncio oauth2 oauth fastapi
Platform: UNKNOWN
Classifier: Intended Audience :: Information Technology
Classifier: Intended Audience :: System Administrators
Classifier: Operating System :: OS Independent
Classifier: Programming Language :: Python :: 3
Classifier: Programming Language :: Python
Classifier: Topic :: Internet
Classifier: Topic :: Software Development :: Libraries :: Application Frameworks
Classifier: Topic :: Software Development :: Libraries :: Python Modules
Classifier: Topic :: Software Development :: Libraries
Classifier: Topic :: Software Development
Classifier: Typing :: Typed
Classifier: Development Status :: 1 - Planning
Classifier: Environment :: Web Environment
Classifier: Framework :: AsyncIO
Classifier: Intended Audience :: Developers
Classifier: License :: OSI Approved :: MIT License
Classifier: Programming Language :: Python :: 3 :: Only
Classifier: Programming Language :: Python :: 3.6
Classifier: Programming Language :: Python :: 3.7
Classifier: Programming Language :: Python :: 3.8
Classifier: Topic :: Internet :: WWW/HTTP :: HTTP Servers
Classifier: Topic :: Internet :: WWW/HTTP
Requires-Python: >=3.6.0
Provides-Extra: dev
Requires-Dist: fastapi (==0.70.1) ; extra == 'dev'
Requires-Dist: aioauth (==1.3.0) ; extra == 'dev'
Requires-Dist: uvicorn (==0.16.0) ; extra == 'dev'
Requires-Dist: wheel ; extra == 'dev'
Requires-Dist: twine (==3.7.1) ; extra == 'dev'
Requires-Dist: pydantic[dotenv] (==1.8.2) ; extra == 'dev'
Requires-Dist: asyncpg (==0.25.0) ; extra == 'dev'
Requires-Dist: SQLAlchemy[asyncio] (==1.4.28) ; extra == 'dev'
Requires-Dist: orjson (==3.6.5) ; extra == 'dev'
Requires-Dist: python-jose[pycryptodome] (==3.3.0) ; extra == 'dev'
Requires-Dist: python-multipart (==0.0.5) ; extra == 'dev'
Requires-Dist: alembic (==1.7.5) ; extra == 'dev'
Requires-Dist: sqlmodel (==0.0.5) ; extra == 'dev'
Requires-Dist: async-asgi-testclient (==1.4.9) ; extra == 'dev'
Requires-Dist: pre-commit (==2.16.0) ; extra == 'dev'
Requires-Dist: pytest (==6.2.5) ; extra == 'dev'
Requires-Dist: pytest-asyncio (==0.16.0) ; extra == 'dev'
Requires-Dist: pytest-cov (==3.0.0) ; extra == 'dev'
Requires-Dist: pytest-env (==0.6.2) ; extra == 'dev'
Requires-Dist: pytest-sugar (==0.9.4) ; extra == 'dev'
Requires-Dist: testfixtures (==6.18.3) ; extra == 'dev'
Requires-Dist: bump2version (==1.0.1) ; extra == 'dev'
